AUTHORS.rst
CONTRIBUTING.rst
HISTORY.rst
LICENSE
MANIFEST.in
README.rst
setup.cfg
setup.py
cenotes_cli/__init__.py
cenotes_cli/cli.py
cenotes_cli/crypto.py
cenotes_cli/remote.py
cenotes_cli.egg-info/PKG-INFO
cenotes_cli.egg-info/SOURCES.txt
cenotes_cli.egg-info/dependency_links.txt
cenotes_cli.egg-info/entry_points.txt
cenotes_cli.egg-info/not-zip-safe
cenotes_cli.egg-info/requires.txt
cenotes_cli.egg-info/top_level.txt