Metadata-Version: 1.1
Name: cenotes-cli
Version: 0.5.1
Summary: Cenotes command line application and libraries
Home-page: https://github.com/ioparaskev/cenotes_cli
Author: John Paraskevopoulos
Author-email: ioparaskev@gmail.com
License: GNU General Public License v3
Keywords: cenotes_cli
Platform: UNKNOWN
Classifier: Development Status :: 4 - Beta
Classifier: Intended Audience :: Developers
Classifier: License :: OSI Approved :: GNU General Public License v3 (GPLv3)
Classifier: Natural Language :: English
Classifier: Programming Language :: Python :: 3
Classifier: Programming Language :: Python :: 3.4
Classifier: Programming Language :: Python :: 3.5
Classifier: Programming Language :: Python :: 3.6
